organic/__init__.py
organic/organic.py
OrganicOI-0.0.29.dist-info/METADATA
OrganicOI-0.0.29.dist-info/WHEEL
OrganicOI-0.0.29.dist-info/top_level.txt
OrganicOI-0.0.29.dist-info/RECORD
