Metadata-Version: 2.1
Name: OrganicOI
Version: 0.0.29
Summary: An image reconstuction algorithm using GANs
Home-page: https://github.com/kluskaj/Organic
Author: Jacques Kluska
Author-email: jacques.kluska@kuleuven.be
Classifier: Programming Language :: Python :: 3
Classifier: Operating System :: OS Independent
Classifier: License :: OSI Approved :: MIT License
Requires-Dist: astropy
Requires-Dist: matplotlib
Requires-Dist: numpy
Requires-Dist: scikit-learn
Requires-Dist: scipy
Requires-Dist: keras
Requires-Dist: tensorflow
Requires-Dist: readoifits
